README.rst
setup.py
unittest_sandbox/__init__.py
unittest_sandbox/decorators.py
unittest_sandbox/patcher.py
unittest_sandbox/socket.py
unittest_sandbox.egg-info/PKG-INFO
unittest_sandbox.egg-info/SOURCES.txt
unittest_sandbox.egg-info/dependency_links.txt
unittest_sandbox.egg-info/top_level.txt