Metadata-Version: 1.1
Name: unittest-sandbox
Version: 1.1.0
Summary: unittest_sandbox provides a @sandbox decorator which ensures unit test methods do not make any socket/web requests during test execution.
Home-page: https://github.com/mikeengland/unittest_sandbox
Author: Michael England
Author-email: UNKNOWN
License: Apache License Version 2.0
Keywords: unittest unittests testcase sandbox internet block decorator socket requests urllib
Platform: UNKNOWN
Classifier: License :: OSI Approved :: Apache Software License
Classifier: Development Status :: 5 - Production/Stable
Classifier: Intended Audience :: Developers
Classifier: Programming Language :: Python :: 3
Classifier: Topic :: Software Development :: Libraries :: Python Modules
Classifier: Operating System :: POSIX
Classifier: Operating System :: MacOS :: MacOS X
Classifier: Operating System :: Microsoft :: Windows
